django_pgjsonb
