Metadata-Version: 1.0
Name: django-pgjsonb
Version: 0.0.8
Summary: Django Postgres JSONB Fields support with lookups
Home-page: UNKNOWN
Author: Jay Young(yjmade)
Author-email: dev@yjmade.net
License: UNKNOWN
Platform: UNKNOWN
